pywavelet/__init__.py
pywavelet/_version.py
pywavelet/backend.py
pywavelet/logger.py
pywavelet/transforms/__init__.py
pywavelet/transforms/phi_computer.py
pywavelet/transforms/cupy/__init__.py
pywavelet/transforms/cupy/forward/__init__.py
pywavelet/transforms/cupy/forward/from_freq.py
pywavelet/transforms/cupy/forward/from_time.py
pywavelet/transforms/cupy/forward/main.py
pywavelet/transforms/cupy/inverse/__init__.py
pywavelet/transforms/cupy/inverse/main.py
pywavelet/transforms/cupy/inverse/to_freq.py
pywavelet/transforms/jax/__init__.py
pywavelet/transforms/jax/forward/__init__.py
pywavelet/transforms/jax/forward/from_freq.py
pywavelet/transforms/jax/forward/from_time.py
pywavelet/transforms/jax/forward/main.py
pywavelet/transforms/jax/inverse/__init__.py
pywavelet/transforms/jax/inverse/main.py
pywavelet/transforms/jax/inverse/to_freq.py
pywavelet/transforms/numpy/__init__.py
pywavelet/transforms/numpy/forward/__init__.py
pywavelet/transforms/numpy/forward/from_freq.py
pywavelet/transforms/numpy/forward/from_time.py
pywavelet/transforms/numpy/forward/main.py
pywavelet/transforms/numpy/inverse/__init__.py
pywavelet/transforms/numpy/inverse/main.py
pywavelet/transforms/numpy/inverse/to_freq.py
pywavelet/transforms/numpy/inverse/to_time.py
pywavelet/types/__init__.py
pywavelet/types/common.py
pywavelet/types/frequencyseries.py
pywavelet/types/plotting.py
pywavelet/types/timeseries.py
pywavelet/types/wavelet.py
pywavelet/types/wavelet_bins.py
pywavelet/utils/__init__.py
pywavelet/utils/analysis.py
pywavelet/utils/timing_cli/__init__.py
pywavelet/utils/timing_cli/cli.py
pywavelet/utils/timing_cli/collect_runtimes.py
pywavelet/utils/timing_cli/plot.py
pywavelet-0.2.8.dist-info/METADATA
pywavelet-0.2.8.dist-info/WHEEL
pywavelet-0.2.8.dist-info/entry_points.txt
pywavelet-0.2.8.dist-info/top_level.txt
pywavelet-0.2.8.dist-info/RECORD
