Metadata-Version: 2.4
Name: pywavelet
Version: 0.2.8
Summary: WDM wavelet transform your time/freq series!
Author-email: Pywavelet Team <avi.vajpeyi@gmail.com>
Project-URL: Homepage, https://pywavelet.github.io/pywavelet/
Project-URL: Bug Reports, https://pywavelet.com/pywavelet/pywavelet/issues
Project-URL: Source, https://github.com/pywavelet/pywavelet/
Classifier: Development Status :: 3 - Alpha
Classifier: Intended Audience :: Science/Research
Classifier: License :: OSI Approved :: MIT License
Classifier: Operating System :: OS Independent
Classifier: Programming Language :: Python :: 3.8
Requires-Python: >=3.10
Requires-Dist: numpy
Requires-Dist: numba
Requires-Dist: scipy
Requires-Dist: matplotlib
Requires-Dist: tqdm
Requires-Dist: rich
Requires-Dist: rocket-fft
Requires-Dist: astropy>=5.2.1
Requires-Dist: jaxtyping
Requires-Dist: beartype
Requires-Dist: click
Provides-Extra: jax
Requires-Dist: jax; extra == "jax"
Provides-Extra: cupy
Requires-Dist: cupy; extra == "cupy"
Provides-Extra: dev
Requires-Dist: pytest>=6.0; extra == "dev"
Requires-Dist: pytest-cov>=4.1.0; extra == "dev"
Requires-Dist: pre-commit; extra == "dev"
Requires-Dist: flake8>=5.0.4; extra == "dev"
Requires-Dist: black>=22.12.0; extra == "dev"
Requires-Dist: black[jupyter]>=22.12.0; extra == "dev"
Requires-Dist: isort; extra == "dev"
Requires-Dist: mypy; extra == "dev"
Requires-Dist: jupyter-book; extra == "dev"
Requires-Dist: GitPython; extra == "dev"
Requires-Dist: nbconvert; extra == "dev"
Requires-Dist: pytest-click; extra == "dev"
